spacedirectory/__init__.py
spacedirectory/cli.py
spacedirectory/directory.py
spacedirectory/space.py
spacedirectory/tools.py
spacedirectory/views.py
spacedirectory/models/__init__.py
spacedirectory/models/directory.py
spacedirectory/models/space.py
spacedirectory-0.0.5.dist-info/DESCRIPTION.rst
spacedirectory-0.0.5.dist-info/METADATA
spacedirectory-0.0.5.dist-info/RECORD
spacedirectory-0.0.5.dist-info/WHEEL
spacedirectory-0.0.5.dist-info/entry_points.txt
spacedirectory-0.0.5.dist-info/metadata.json
spacedirectory-0.0.5.dist-info/top_level.txt
