Metadata-Version: 2.0
Name: spacedirectory
Version: 0.0.5
Summary: Get informations about (hacker)spaces from the Spacedirectory (or a Space API)
Home-page: https://framagit.org/SebGen/spacedirectory
Author: Sébastien Gendre
Author-email: seb@k-7.ch
License: GPLv3
Keywords: spacedirectory space-api
Platform: UNKNOWN
Classifier: Development Status :: 4 - Beta
Classifier: License :: OSI Approved :: GNU General Public License v3 (GPLv3)
Classifier: Operating System :: OS Independent
Classifier: Topic :: Software Development :: Libraries :: Python Modules
Classifier: Topic :: Internet
Classifier: Programming Language :: Python
Classifier: Programming Language :: Python :: 3.4
Classifier: Programming Language :: Python :: 3.5
Classifier: Programming Language :: Python :: 3.6
Requires-Python: >=3
Requires-Dist: ansicolors (==1.1.8)
